par3_align/align_books.py
par3_align/ansi2html.sh
par3_align/similarity/__init__.py
par3_align/similarity/sim/sim.pt
par3_align/similarity/sim/sim.sp.30k.model
par3_align/similarity/sim_models.py
par3_align/similarity/sim_utils.py
par3_align/similarity/test_sim.py
par3_align/utils.py
par3_align-0.1.2.dist-info/LICENSE
par3_align-0.1.2.dist-info/WHEEL
par3_align-0.1.2.dist-info/METADATA
par3_align-0.1.2.dist-info/RECORD
