Metadata-Version: 2.1
Name: par3-align
Version: 0.1.2
Summary: Scripts to align books and process the Par3 dataset.
License: MIT
Author: Kalpesh Krishna
Requires-Python: >=3.7,<4.0
Classifier: License :: OSI Approved :: MIT License
Classifier: Programming Language :: Python :: 3
Classifier: Programming Language :: Python :: 3.7
Classifier: Programming Language :: Python :: 3.8
Classifier: Programming Language :: Python :: 3.9
Classifier: Programming Language :: Python :: 3.10
Requires-Dist: nltk (>=3.7,<4.0)
Requires-Dist: sentencepiece (>=0.1.97,<0.2.0)
Requires-Dist: spacy (>=3.4.1,<4.0.0)
Requires-Dist: torch (>=1.12.1,<2.0.0)
